code_validator/__init__.py
code_validator/__main__.py
code_validator/cli.py
code_validator/config.py
code_validator/core.py
code_validator/exceptions.py
code_validator/output.py
code_validator/components/__init__.py
code_validator/components/ast_utils.py
code_validator/components/definitions.py
code_validator/components/factories.py
code_validator/components/scope_handler.py
code_validator/components/typo_detection/__init__.py
code_validator/components/typo_detection/algorithms.py
code_validator/components/typo_detection/detector.py
code_validator/components/typo_detection/formatters.py
code_validator/components/typo_detection/scope_analyzer.py
code_validator/rules_library/__init__.py
code_validator/rules_library/basic_rules.py
code_validator/rules_library/constraint_logic.py
code_validator/rules_library/selector_nodes.py
python_code_validator-0.4.0.dist-info/licenses/LICENSE
python_code_validator-0.4.0.dist-info/METADATA
python_code_validator-0.4.0.dist-info/WHEEL
python_code_validator-0.4.0.dist-info/entry_points.txt
python_code_validator-0.4.0.dist-info/top_level.txt
python_code_validator-0.4.0.dist-info/RECORD
