Metadata-Version: 2.4
Name: python-code-validator
Version: 0.4.0
Summary: A flexible, AST-based framework for static validation of Python code using declarative JSON rules.
Author-email: Qu1nel <covach.qn@gmail.com>
License: MIT License
Project-URL: Homepage, https://github.com/Qu1nel/PythonCodeValidator
Project-URL: Documentation, https://pythoncodevalidator.readthedocs.io/en/latest/
Project-URL: Bug Tracker, https://github.com/Qu1nel/PythonCodeValidator/issues
Keywords: validation,linter,static analysis,testing,education,ast
Classifier: Development Status :: 4 - Beta
Classifier: Intended Audience :: Developers
Classifier: Intended Audience :: Education
Classifier: Programming Language :: Python :: 3
Classifier: Programming Language :: Python :: 3.11
Classifier: Programming Language :: Python :: 3.12
Classifier: License :: OSI Approved :: MIT License
Classifier: Operating System :: OS Independent
Classifier: Topic :: Software Development :: Quality Assurance
Classifier: Topic :: Software Development :: Testing
Classifier: Topic :: Education
Requires-Python: >=3.11
License-File: LICENSE
Requires-Dist: flake8>=7.0.0
Provides-Extra: dev
Requires-Dist: ruff>=0.4.0; extra == "dev"
Requires-Dist: build; extra == "dev"
Requires-Dist: twine; extra == "dev"
Requires-Dist: coverage[toml]>=7.5.0; extra == "dev"
Provides-Extra: docs
Requires-Dist: sphinx>=7.0.0; extra == "docs"
Requires-Dist: furo; extra == "docs"
Requires-Dist: myst-parser; extra == "docs"
Requires-Dist: sphinx-design; extra == "docs"
Dynamic: license-file
